aiomatter/__init__.py
aiomatter/aiologger.py
aiomatter/bot.py
aiomatter/driver.py
aiomatter/events.py
aiomatter/plugin.py
aiomatter/settings.py
aiomatter/wrappers.py
aiomatter/input/__init__.py
aiomatter/input/input_file.py
aiomatter/schemas/__init__.py
aiomatter/schemas/post_events.py
aiomatter/schemas/system_events.py
aiomatter/schemas/user.py
aiomatter/state/__init__.py
aiomatter/state/base.py
aiomatter/state/fsm_context.py
aiomatter/state/middleware.py
aiomatter/state/strategy.py
aiomatter-0.2.0.dist-info/METADATA
aiomatter-0.2.0.dist-info/WHEEL
aiomatter-0.2.0.dist-info/top_level.txt
aiomatter-0.2.0.dist-info/RECORD
