Metadata-Version: 2.2
Name: aiomatter
Version: 0.2.0
Summary: Mattermost async bot
Author-email: Vladimir Savelev <ruslawsav@gmail.com>, Polina Grunina <linaborisovsky@gmail.com>
Classifier: Programming Language :: Python :: 3
Classifier: License :: OSI Approved :: MIT License
Classifier: Operating System :: OS Independent
Requires-Python: >=3.11
Requires-Dist: websockets>=13.1
Requires-Dist: pydantic>=2.9.2
Requires-Dist: aiohttp>=3.10.10
